jgwill/__init__.py
jgwill/coaiapy/bump.py
jgwill/coaiapy/example_smart_cache_usage.py
jgwill/coaiapy/setup.py
jgwill/coaiapy/coaiapy/__init__.py
jgwill/coaiapy/coaiapy/coaiacli.py
jgwill/coaiapy/coaiapy/coaiamodule.py
jgwill/coaiapy/coaiapy/cofuse.py
jgwill/coaiapy/coaiapy/environment.py
jgwill/coaiapy/coaiapy/mobile_template.py
jgwill/coaiapy/coaiapy/pipeline.py
jgwill/coaiapy/coaiapy/syntation.py
jgwill/coaiapy/coaiapy/test_cli_fetch.py
jgwill/coaiapy/tests/run_all_tests.py
jgwill/coaiapy/tests/test_env_functionality.py
jgwill/coaiapy/tests/test_langfuse_env_integration.py
jgwill/coaiapy/tests/test_mobile_template_engine.py
jgwill/coaiapy/tests/test_mobile_workflows.py
jgwill/coaiapy/tests/test_performance_benchmarks.py
jgwill/coaiapy/tests/test_pipeline_templates.py
jgwill/coaiapy/tests/test_pythonista_compatibility.py
jgwill/coaiapy/tests/test_real_langfuse_integration.py
jgwill/coaiapy/tests/test_suite.py
jgwill/storytelling/storytelling/__init__.py
jgwill/storytelling/storytelling/__main__.py
jgwill/storytelling/storytelling/cli.py
jgwill/storytelling/storytelling/core.py
jgwill/storytelling/tests/__init__.py
jgwill/storytelling/tests/test_cli.py
jgwill/storytelling/tests/test_core.py
jgwill-0.0.1.dist-info/licenses/LICENSE
jgwill-0.0.1.dist-info/METADATA
jgwill-0.0.1.dist-info/WHEEL
jgwill-0.0.1.dist-info/entry_points.txt
jgwill-0.0.1.dist-info/top_level.txt
jgwill-0.0.1.dist-info/RECORD
