Metadata-Version: 2.4
Name: jgwill
Version: 0.0.1
Summary: A basic Python package to reserve 'jgwill' at pypi.org
Author-email: Your Name <your.email@example.com>
Project-URL: Homepage, https://github.com/yourusername/jgwill
Project-URL: Bug Tracker, https://github.com/yourusername/jgwill/issues
Keywords: jgwill,just-good-will,coaiapy,storytelling
Classifier: Programming Language :: Python :: 3
Classifier: License :: OSI Approved :: MIT License
Classifier: Operating System :: OS Independent
Requires-Python: >=3.8
License-File: LICENSE
Dynamic: license-file
